kaomoji/__init__.py
kaomoji/__main__.py
kaomoji/config.py
kaomoji/kaomoji.py
kaomoji-0.1.0.dist-info/LICENSE.md
kaomoji-0.1.0.dist-info/WHEEL
kaomoji-0.1.0.dist-info/METADATA
kaomoji-0.1.0.dist-info/RECORD
