Metadata-Version: 2.1
Name: kaomoji
Version: 0.1.0
Summary: Create procedurally generated kaomoji (i.e., Japanese emoticons) using Python! \(^ヮ^)/
Home-page: https://github.com/keithdowd/kaomoji
License: MIT
Keywords: kaomoji,emoji,emoticon
Author: Keith Dowd
Author-email: keith.dowd@gmail.com
Requires-Python: >=3.6,<4.0
Classifier: Environment :: Console
Classifier: Intended Audience :: Developers
Classifier: License :: OSI Approved :: MIT License
Classifier: Natural Language :: English
Classifier: Operating System :: OS Independent
Classifier: Programming Language :: Python :: 3
Classifier: Programming Language :: Python :: 3.6
Classifier: Programming Language :: Python :: 3.7
Classifier: Programming Language :: Python :: 3.8
Classifier: Topic :: Communications :: Chat
Classifier: Topic :: Games/Entertainment
Classifier: Topic :: Software Development :: Libraries :: Python Modules
Project-URL: Documentation, https://github.com/keithdowd/kaomoji
Project-URL: Repository, https://github.com/keithdowd/kaomoji
